datastock/_DataCollection_utils.py
datastock/__init__.py
datastock/_class.py
datastock/_class0.py
datastock/_class1.py
datastock/_class1_binning.py
datastock/_class1_check.py
datastock/_class1_color_touch.py
datastock/_class1_compute.py
datastock/_class1_domain.py
datastock/_class1_interpolate.py
datastock/_class1_show.py
datastock/_class1_uniformize.py
datastock/_class2.py
datastock/_class2_interactivity.py
datastock/_class3.py
datastock/_direct_calls.py
datastock/_export_dataframe.py
datastock/_find_plateau.py
datastock/_generic_check.py
datastock/_generic_utils.py
datastock/_generic_utils_plot.py
datastock/_plot_BvsA_as_distribution.py
datastock/_plot_BvsA_as_distribution_check.py
datastock/_plot_as_array.py
datastock/_plot_as_array_1d.py
datastock/_plot_as_array_234d.py
datastock/_plot_as_mobile_lines.py
datastock/_plot_as_profile1d.py
datastock/_plot_correlations.py
datastock/_plot_old_backup.py
datastock/_plot_text.py
datastock/_saveload.py
datastock/_version.py
datastock/version.py
datastock/tests/__init__.py
datastock/tests/prepublish.py
datastock/tests/test_01_DataStock.py
datastock/tests/output/__init__.py
datastock-0.0.55.dist-info/licenses/LICENSE.txt
datastock-0.0.55.dist-info/METADATA
datastock-0.0.55.dist-info/WHEEL
datastock-0.0.55.dist-info/entry_points.txt
datastock-0.0.55.dist-info/top_level.txt
datastock-0.0.55.dist-info/RECORD
