Metadata-Version: 2.4
Name: datastock
Version: 0.0.55
Summary: Generic handler for multiple heterogenous numpy arrays and subclasses
Author-email: Didier VEZINET <didier.vezinet@gmail.com>
Maintainer-email: Didier VEZINET <didier.vezinet@gmail.com>
License: MIT
Project-URL: Homepage, https://github.com/ToFuProject/datastock
Project-URL: Issues, https://github.com/ToFuProject/datastock/issues
Keywords: data,analysis,interactive,heterogeneous arrays,numpy,Collection
Classifier: Development Status :: 5 - Production/Stable
Classifier: Intended Audience :: Science/Research
Classifier: Programming Language :: Python :: 3
Classifier: Programming Language :: Python :: 3.6
Classifier: Programming Language :: Python :: 3.7
Classifier: Programming Language :: Python :: 3.8
Classifier: Programming Language :: Python :: 3.9
Classifier: Programming Language :: Python :: 3.10
Classifier: Programming Language :: Python :: 3.11
Classifier: Natural Language :: English
Requires-Python: >=3.8
License-File: LICENSE.txt
Requires-Dist: numpy<1.25
Requires-Dist: scipy
Requires-Dist: matplotlib
Requires-Dist: astropy
Provides-Extra: linting
Requires-Dist: ruff; extra == "linting"
Provides-Extra: formatting
Requires-Dist: ruff; extra == "formatting"
Dynamic: license-file
